PYbleau/__init__.py
PYbleau-1.2.dist-info/DESCRIPTION.rst
PYbleau-1.2.dist-info/METADATA
PYbleau-1.2.dist-info/RECORD
PYbleau-1.2.dist-info/WHEEL
PYbleau-1.2.dist-info/metadata.json
PYbleau-1.2.dist-info/top_level.txt
