Metadata-Version: 2.0
Name: PYbleau
Version: 1.2
Summary: A quick way to visualize and obtain quick insights about your dataset.
Home-page: https://github.com/BobbyTaylor82/PYbleau
Author: BobbyTaylor82
Author-email: bltxr9@gmail.com
License: MIT
Platform: UNKNOWN
